garnett/__init__.py
garnett/apps.py
garnett/context.py
garnett/context_processors.py
garnett/exceptions.py
garnett/expressions.py
garnett/ext/__init__.py
garnett/ext/drf.py
garnett/ext/filters.py
garnett/ext/reversion.py
garnett/fields.py
garnett/lookups.py
garnett/middleware.py
garnett/migrate.py
garnett/mixins.py
garnett/patch.py
garnett/selectors.py
garnett/serializers/__init__.py
garnett/serializers/base.py
garnett/serializers/json.py
garnett/templates/admin/change_form_object_tools.html
garnett/templates/garnett/language_selector.html
garnett/templatetags/__init__.py
garnett/templatetags/garnett.py
garnett/translatedstr.py
garnett/utils.py
django_garnett-0.5.4.dist-info/LICENCE.txt
django_garnett-0.5.4.dist-info/METADATA
django_garnett-0.5.4.dist-info/WHEEL
django_garnett-0.5.4.dist-info/RECORD
