Metadata-Version: 2.1
Name: django-garnett
Version: 0.5.4
Summary: Simple translatable Django fields
License: BSD-3-Clause
Author: Aristotle Metadata Enterprises
Requires-Python: >=3.12,<4.0
Classifier: License :: OSI Approved :: BSD License
Classifier: Programming Language :: Python :: 3
Classifier: Programming Language :: Python :: 3.12
Classifier: Programming Language :: Python :: 3.13
Requires-Dist: django (>=4.2)
Requires-Dist: langcodes (>=3.3.0,<3.4.0)
Requires-Dist: language-data (>=1.0.1,<1.1.0)
